LICENSE
MANIFEST.in
Makefile
README
setup.cfg
setup.py
Flask_BabelEx.egg-info/PKG-INFO
Flask_BabelEx.egg-info/SOURCES.txt
Flask_BabelEx.egg-info/dependency_links.txt
Flask_BabelEx.egg-info/not-zip-safe
Flask_BabelEx.egg-info/requires.txt
Flask_BabelEx.egg-info/top_level.txt
docs/Makefile
docs/conf.py
docs/index.rst
docs/make.bat
docs/_static/flask-babel.png
docs/_themes/.git
docs/_themes/.gitignore
docs/_themes/LICENSE
docs/_themes/README
docs/_themes/flask_theme_support.py
docs/_themes/flask/layout.html
docs/_themes/flask/relations.html
docs/_themes/flask/theme.conf
docs/_themes/flask/static/flasky.css_t
docs/_themes/flask/static/small_flask.css
docs/_themes/flask_small/layout.html
docs/_themes/flask_small/theme.conf
docs/_themes/flask_small/static/flasky.css_t
flask_babelex/__init__.py
tests/babel.cfg
tests/tests.py
tests/translations/messages.pot
tests/translations/test.pot
tests/translations/de/LC_MESSAGES/messages.mo
tests/translations/de/LC_MESSAGES/messages.po
tests/translations/de/LC_MESSAGES/test.mo
tests/translations/de/LC_MESSAGES/test.po