Metadata-Version: 1.0
Name: Flask-BabelEx
Version: 0.1
Summary: Adds i18n/l10n support to Flask applications
Home-page: http://github.com/mrjoes/flask-babelex
Author: Serge S. Koval
Author-email: serge.koval+github@gmail.com
License: BSD
Platform: any
Classifier: Development Status :: 4 - Beta
Classifier: Environment :: Web Environment
Classifier: Intended Audience :: Developers
Classifier: License :: OSI Approved :: BSD License
Classifier: Operating System :: OS Independent
Classifier: Programming Language :: Python
Classifier: Topic :: Internet :: WWW/HTTP :: Dynamic Content
Classifier: Topic :: Software Development :: Libraries :: Python Modules
